census_consumer_complaint/__init__.py
census_consumer_complaint/component/__init__.py
census_consumer_complaint/component/component.py
census_consumer_complaint/component/data_ingestion.py
census_consumer_complaint/component/data_preprocessing.py
census_consumer_complaint/component/data_validation.py
census_consumer_complaint/component/model_evaluation.py
census_consumer_complaint/component/model_pusher.py
census_consumer_complaint/component/model_trainer.py
census_consumer_complaint/component/feature_engineering/__init__.py
census_consumer_complaint/component/feature_engineering/feature_engineering.py
census_consumer_complaint/component/model_training/__init__.py
census_consumer_complaint/component/model_training/trainer.py
census_consumer_complaint/config/__init__.py
census_consumer_complaint/config/configuration.py
census_consumer_complaint/custom_component/__init__.py
census_consumer_complaint/custom_component/component.py
census_consumer_complaint/custom_component/example_gen/__init__.py
census_consumer_complaint/custom_component/example_gen/remote_zip_csv_example_gen/__init__.py
census_consumer_complaint/custom_component/example_gen/remote_zip_csv_example_gen/component.py
census_consumer_complaint/custom_component/example_gen/remote_zip_csv_example_gen/executor.py
census_consumer_complaint/custom_component/example_gen/remote_zip_csv_example_gen/executor_test.py
census_consumer_complaint/exception/__init__.py
census_consumer_complaint/exception/exception.py
census_consumer_complaint/executor/__init__.py
census_consumer_complaint/executor/zip_csv_executor.py
census_consumer_complaint/orchestrator/__init__.py
census_consumer_complaint/orchestrator/airflow_orchestrator.py
census_consumer_complaint/orchestrator/apache_beam_orchestrator.py
census_consumer_complaint/orchestrator/interactive_context_runner.py
census_consumer_complaint/orchestrator/local_orchestrator.py
census_consumer_complaint/types/__init__.py
census_consumer_complaint/types/types.py
census_consumer_complaint-0.1.0.dist-info/METADATA
census_consumer_complaint-0.1.0.dist-info/WHEEL
census_consumer_complaint-0.1.0.dist-info/top_level.txt
census_consumer_complaint-0.1.0.dist-info/RECORD
