Metadata-Version: 2.1
Name: census-consumer-complaint
Version: 0.1.0
Summary: Project has been completed.
Author: Avnish Yadav
License: MIT
Requires-Dist: tfx
Requires-Dist: apache-beam[interactive]
Requires-Dist: apache-airflow
